{
  "RSpec": {
    "coverage": {
      "/Users/Student/wk6challenge/app.rb": {
        "lines": [
          1,
          1,
          1,
          1,
          1,
          0,
          null,
          1,
          1,
          null,
          null,
          1,
          4,
          4,
          null,
          null,
          1,
          null,
          1,
          null,
          1,
          null,
          null,
          1,
          null
        ]
      },
      "/Users/Student/wk6challenge/lib/messages.rb": {
        "lines": [
          1,
          null,
          1,
          null,
          null,
          1,
          5,
          5,
          null,
          0,
          null,
          null,
          5,
          null,
          null,
          1,
          7,
          7,
          null,
          0,
          null,
          null,
          7,
          7,
          8,
          null,
          null,
          null,
          null
        ]
      },
      "/Users/Student/wk6challenge/spec/features/creating_messages_spec.rb": {
        "lines": [
          1,
          1,
          1,
          1,
          null,
          null,
          null,
          1,
          1,
          1,
          1,
          null,
          1,
          null,
          null,
          null,
          1,
          1,
          1,
          1,
          1,
          1,
          null,
          null,
          null
        ]
      },
      "/Users/Student/wk6challenge/spec/features/test_page_spec.rb": {
        "lines": [
          1,
          null,
          1,
          1,
          1,
          1,
          null,
          null
        ]
      },
      "/Users/Student/wk6challenge/spec/messages_spec.rb": {
        "lines": [
          1,
          null,
          1,
          1,
          1,
          1,
          null,
          null,
          null,
          1,
          1,
          1,
          1,
          1,
          1,
          1,
          null,
          1,
          null,
          null,
          null,
          null
        ]
      }
    },
    "timestamp": 1628862227
  }
}
